quoter/__init__.py
quoter/data/__init__.py
quoter/data/dbconnect.py
quoter/model/__init__.py
quoter/model/quote.py
scripts/__init__.py
scripts/pyquoter.py
test/__init__.py
test/database_test.py
pyquoter-1.0.0.dist-info/METADATA
pyquoter-1.0.0.dist-info/WHEEL
pyquoter-1.0.0.dist-info/entry_points.txt
pyquoter-1.0.0.dist-info/top_level.txt
pyquoter-1.0.0.dist-info/RECORD
