Metadata-Version: 2.1
Name: pyquoter
Version: 1.0.0
Summary: UNKNOWN
Home-page: https://github.com/joshpetit/pyquoter
Author: Joshua Petitma
Author-email: joshua@joshpetit.dev
License: UNKNOWN
Platform: UNKNOWN
Classifier: Programming Language :: Python :: 3
Classifier: Programming Language :: Python :: 3.8
Classifier: License :: OSI Approved :: MIT License
Classifier: Operating System :: OS Independent
Requires-Python: >=3.6
